[
  {
    "arguments": [
      "/usr/bin/g++",
      "-c",
      "-Ideps/include",
      "-Iinclude",
      "-o",
      "bin/src/Engine/RenderEngine.o",
      "src/Engine/RenderEngine.cpp"
    ],
    "directory": "/home/domenic/dev/DDE",
    "file": "/home/domenic/dev/DDE/src/Engine/RenderEngine.cpp",
    "output": "/home/domenic/dev/DDE/bin/src/Engine/RenderEngine.o"
  },
  {
    "arguments": [
      "/usr/bin/g++",
      "-c",
      "-Ideps/include",
      "-Iinclude",
      "-o",
      "bin/src/dde.o",
      "src/dde.cpp"
    ],
    "directory": "/home/domenic/dev/DDE",
    "file": "/home/domenic/dev/DDE/src/dde.cpp",
    "output": "/home/domenic/dev/DDE/bin/src/dde.o"
  }
]
